GRADitude-0.1.3.data/scripts/graditude
graditudelib/Nearest_Neighbors.py
graditudelib/__init__.py
graditudelib/clustering.py
graditudelib/clustering_proteins.py
graditudelib/correlation_between_genes.py
graditudelib/correlation_replicates_sequencing_data.py
graditudelib/correlation_rna_protein.py
graditudelib/correlation_specific_gene.py
graditudelib/dimension_reduction_proteins.py
graditudelib/distribution_correlation.py
graditudelib/dropping_specific_columns.py
graditudelib/elbow_curve.py
graditudelib/extract_attribute_column.py
graditudelib/finding_complexes_complete.py
graditudelib/generate_html.py
graditudelib/heatmap.py
graditudelib/histograms_of_fractions.py
graditudelib/interactive_plots.py
graditudelib/merge_exctract_attributes.py
graditudelib/merge_features.py
graditudelib/min_row_sum.py
graditudelib/min_row_sum_ercc_table.py
graditudelib/move_columns.py
graditudelib/normalize.py
graditudelib/normalize_table_spikein.py
graditudelib/pca_analysis.py
graditudelib/plot_network_graph.py
graditudelib/projectcreator.py
graditudelib/robust_regression.py
graditudelib/scaling.py
graditudelib/selecting_ncRNAs.py
graditudelib/silhouette.py
graditudelib/silhouette_prova.py
graditudelib/size_factor.py
graditudelib/t_sne_colored_list_clustering_features.py
graditudelib/umap_analysis.py
graditudelib/visualizing_kinetics.py
GRADitude-0.1.3.dist-info/LICENSE.txt
GRADitude-0.1.3.dist-info/METADATA
GRADitude-0.1.3.dist-info/WHEEL
GRADitude-0.1.3.dist-info/top_level.txt
GRADitude-0.1.3.dist-info/RECORD
